glooey/__init__.py
glooey/buttons.py
glooey/containers.py
glooey/dialogs.py
glooey/helpers.py
glooey/images.py
glooey/misc.py
glooey/root.py
glooey/scrolling.py
glooey/text.py
glooey/widget.py
glooey/drawing/__init__.py
glooey/drawing/alignment.py
glooey/drawing/artists.py
glooey/drawing/color.py
glooey/drawing/grid.py
glooey/drawing/stencil.py
glooey/drawing/text.py
glooey/themes/__init__.py
glooey/themes/golden.py
glooey/themes/helpers.py
glooey/themes/kenney.py
glooey/themes/wesnoth.py
glooey/themes/zero_ad.py
glooey/themes/assets/golden/.gitignore
glooey/themes/assets/golden/README
glooey/themes/assets/golden/ui_big_pieces.png
glooey/themes/assets/golden/ui_split.png
glooey/themes/assets/golden/buttons/basic/base_center.png
glooey/themes/assets/golden/buttons/basic/base_left.png
glooey/themes/assets/golden/buttons/basic/base_left_with_ring.png
glooey/themes/assets/golden/buttons/basic/base_right.png
glooey/themes/assets/golden/buttons/basic/base_right_with_ring.png
glooey/themes/assets/golden/buttons/basic/down_center.png
glooey/themes/assets/golden/buttons/basic/down_left.png
glooey/themes/assets/golden/buttons/basic/down_left_with_ring.png
glooey/themes/assets/golden/buttons/basic/down_right.png
glooey/themes/assets/golden/buttons/basic/down_right_with_ring.png
glooey/themes/assets/golden/buttons/fancy/center_base.png
glooey/themes/assets/golden/buttons/fancy/center_down.png
glooey/themes/assets/golden/buttons/fancy/center_over.png
glooey/themes/assets/golden/buttons/fancy/left_base.png
glooey/themes/assets/golden/buttons/fancy/left_down.png
glooey/themes/assets/golden/buttons/fancy/left_over.png
glooey/themes/assets/golden/buttons/fancy/right_base.png
glooey/themes/assets/golden/buttons/fancy/right_down.png
glooey/themes/assets/golden/buttons/fancy/right_over.png
glooey/themes/assets/golden/buttons/radio/checked.png
glooey/themes/assets/golden/buttons/radio/unchecked.png
glooey/themes/assets/golden/buttons/round/blue_base.png
glooey-0.3.5.dist-info/LICENSE.txt
glooey-0.3.5.dist-info/WHEEL
glooey-0.3.5.dist-info/METADATA
glooey-0.3.5.dist-info/RECORD
