Metadata-Version: 2.1
Name: glooey
Version: 0.3.5
Summary: An object-oriented GUI library for pyglet.
Home-page: https://github.com/kxgames/glooey
License: UNKNOWN
Author: Kale Kundert
Author-email: kale@thekunderts.net
Requires-Python: ~=3.6
Classifier: Programming Language :: Python :: 3
Classifier: Topic :: Games/Entertainment
Classifier: Topic :: Software Development :: User Interfaces
Classifier: Topic :: Software Development :: Libraries
Classifier: License :: OSI Approved :: MIT License
Classifier: Intended Audience :: Developers
Requires-Dist: pyglet
Requires-Dist: more_itertools
Requires-Dist: vecrec
Requires-Dist: autoprop
Requires-Dist: pyyaml
Requires-Dist: sphinx>=3.1 ; extra == "docs"
Requires-Dist: sphinx_rtd_theme ; extra == "docs"
Requires-Dist: autoclasstoc ; extra == "docs"
Requires-Dist: pytest ; extra == "tests"
Requires-Dist: pytest-cov ; extra == "tests"
Requires-Dist: coveralls ; extra == "tests"
Project-URL: Bug Tracker, https://github.com/kxgames/glooey/issues
Project-URL: Continuous Integration, https://github.com/kxgames/glooey/actions
Project-URL: Documentation, https://glooey.readthedocs.io/en/latest/
Project-URL: Test Coverage, https://coveralls.io/github/kxgames/glooey
Project-URL: Version Control, https://github.com/kxgames/glooey
Provides-Extra: docs
Provides-Extra: tests
